dfimg/__init__.py
dfimg/dfimg.py
dfimg-0.1.3.dist-info/LICENSE
dfimg-0.1.3.dist-info/METADATA
dfimg-0.1.3.dist-info/WHEEL
dfimg-0.1.3.dist-info/RECORD
