Metadata-Version: 2.3
Name: dfimg
Version: 0.1.3
Summary: A library to convert polars/ pandas dataframes to image.
License: MIT
Keywords: dataframe,image,pandas,polars,pillow
Author: Tapanhaz tapanhaz@gmail.com
Requires-Python: >=3.9,<4.0
Classifier: License :: OSI Approved :: MIT License
Classifier: Programming Language :: Python :: 3
Classifier: Programming Language :: Python :: 3.9
Classifier: Programming Language :: Python :: 3.10
Classifier: Programming Language :: Python :: 3.11
Classifier: Programming Language :: Python :: 3.12
Classifier: Programming Language :: Python :: 3.13
Requires-Dist: beautifulsoup4
Requires-Dist: pandas
Requires-Dist: pillow
Requires-Dist: polars
Requires-Dist: requests
Project-URL: Homepage, https://github.com/Tapanhaz/dfimg
Project-URL: Repository, https://github.com/Tapanhaz/dfimg
